openweathermap/__init__.py
openweathermap/weather.py
openweathermap-0.1.4.dist-info/LICENSE
openweathermap-0.1.4.dist-info/METADATA
openweathermap-0.1.4.dist-info/WHEEL
openweathermap-0.1.4.dist-info/top_level.txt
openweathermap-0.1.4.dist-info/RECORD
